ros2em/__init__.py
ros2em/cli.py
ros2em/backend/__init__.py
ros2em/backend/docker_backend.py
ros2em/core/__init__.py
ros2em/core/delete.py
ros2em/core/init.py
ros2em/core/manager.py
ros2em/core/open.py
ros2em/core/stop.py
ros2em/core/up.py
ros2em/utils/__init__.py
ros2em/utils/docker_utils.py
ros2em/utils/env_utils.py
ros2em/utils/network_utils.py
ros2em-0.2.0.dist-info/licenses/LICENSE
ros2em-0.2.0.dist-info/METADATA
ros2em-0.2.0.dist-info/WHEEL
ros2em-0.2.0.dist-info/entry_points.txt
ros2em-0.2.0.dist-info/top_level.txt
ros2em-0.2.0.dist-info/RECORD
