Metadata-Version: 2.4
Name: ros2em
Version: 0.2.0
Summary: ROS2 Environment Manager
Author-email: Kodo Robotics <kodorobotics@gmail.com>
License:                                  Apache License
Requires-Python: >=3.7
License-File: LICENSE
Requires-Dist: typer[all]
Requires-Dist: rich
Dynamic: license-file
